otmcm_backend/__init__.py
otmcm_backend/core.py
otmcm_backend/example.py
otmcm_backend/utils.py
otmcm_backend/common/__init__.py
otmcm_backend/common/helpers.py
otmcm_backend/common/utils.py
otmcm_backend/common/interfaces/__init__.py
otmcm_backend/common/interfaces/zmq_channel.py
otmcm_backend/common/models/__init__.py
otmcm_backend/common/models/channel_models.py
otmcm_backend/distributor/__init__.py
otmcm_backend/distributor/core.py
otmcm_backend/distributor/models.py
otmcm_backend/distributor_manager/__init__.py
otmcm_backend/distributor_manager/constant.py
otmcm_backend/distributor_manager/core.py
otmcm_backend/distributor_manager/core_old.py
otmcm_backend/distributor_manager/interface.py
otmcm_backend/distributor_manager/models.py
otmcm_backend-0.0.1.data/scripts/otmcm_launch.py
otmcm_backend-0.0.1.dist-info/LICENSE
otmcm_backend-0.0.1.dist-info/METADATA
otmcm_backend-0.0.1.dist-info/WHEEL
otmcm_backend-0.0.1.dist-info/top_level.txt
otmcm_backend-0.0.1.dist-info/RECORD
