Metadata-Version: 2.1
Name: otmcm-backend
Version: 0.0.1
Summary: Backend package for otmcm algotrading environment
Home-page: https://github.com/huankimtran/OTMCM
Author: Huan Tran
Author-email: huankimtran@gmail.com
License: UNKNOWN
Project-URL: Bug Tracker, https://github.com/huankimtran/OTMCM
Platform: UNKNOWN
Classifier: Programming Language :: Python :: 3
Classifier: Operating System :: OS Independent
Requires-Python: >=3.8
License-File: LICENSE
Requires-Dist: pyzmq (>=18.1.1)
